{"prefix": {"collabmap": "http://www.orchid.ac.uk/ontologies/collabmap.owl#", "default": "http://www.collabmap.org/data/local/20140716/"}, "activity": {"CompletionVerification12501": {"prov:startTime": "2012-02-14T03:55:48", "prov:endTime": "2012-02-14T03:55:50", "prov:type": {"$": "collabmap:CompletionVerification", "type": "prov:QUALIFIED_NAME"}}, "CompletionVerification15281": {"prov:startTime": "2012-02-15T23:09:15", "prov:endTime": "2012-02-15T23:09:16", "prov:type": {"$": "collabmap:CompletionVerification", "type": "prov:QUALIFIED_NAME"}}, "CompletionVerification16267": {"prov:startTime": "2012-02-16T15:42:12", "prov:endTime": "2012-02-16T15:42:13", "prov:type": {"$": "collabmap:CompletionVerification", "type": "prov:QUALIFIED_NAME"}}, "CompletionVerification16921": {"prov:startTime": "2012-02-16T18:42:38", "prov:endTime": "2012-02-16T18:42:39", "prov:type": {"$": "collabmap:CompletionVerification", "type": "prov:QUALIFIED_NAME"}}, "CompletionVerification18357": {"prov:startTime": "2012-02-17T15:18:14", "prov:endTime": "2012-02-17T15:18:15", "prov:type": {"$": "collabmap:CompletionVerification", "type": "prov:QUALIFIED_NAME"}}, "CompletionVerification18928": {"prov:startTime": "2012-02-17T21:41:52", "prov:endTime": "2012-02-17T21:42:43", "prov:type": {"$": "collabmap:CompletionVerification", "type": "prov:QUALIFIED_NAME"}}, "CompletionVerification19672": {"prov:startTime": "2012-02-18T15:43:31", "prov:endTime": "2012-02-18T15:43:32", "prov:type": {"$": "collabmap:CompletionVerification", "type": "prov:QUALIFIED_NAME"}}, "CompletionVerification20022": {"prov:startTime": "2012-02-18T21:15:08", "prov:endTime": "2012-02-18T21:15:09", "prov:type": {"$": "collabmap:CompletionVerification", "type": "prov:QUALIFIED_NAME"}}, "RouteIdentification15282": {"prov:startTime": "2012-02-15T23:09:16", "prov:endTime": "2012-02-15T23:09:22", "prov:type": {"$": "collabmap:RouteIdentification", "type": "prov:QUALIFIED_NAME"}}, "RouteIdentification16268": {"prov:startTime": "2012-02-16T15:42:13", "prov:endTime": "2012-02-16T15:42:22", "prov:type": {"$": "collabmap:RouteIdentification", "type": "prov:QUALIFIED_NAME"}}, "RouteVerification12500": {"prov:startTime": "2012-02-14T03:55:46", "prov:endTime": "2012-02-14T03:55:48", "prov:type": {"$": "collabmap:RouteVerification", "type": "prov:QUALIFIED_NAME"}}, "RouteVerification15280": {"prov:startTime": "2012-02-15T23:09:10", "prov:endTime": "2012-02-15T23:09:15", "prov:type": {"$": "collabmap:RouteVerification", "type": "prov:QUALIFIED_NAME"}}, "RouteVerification16266": {"prov:startTime": "2012-02-16T15:41:40", "prov:endTime": "2012-02-16T15:42:12", "prov:type": {"$": "collabmap:RouteVerification", "type": "prov:QUALIFIED_NAME"}}, "RouteVerification16920": {"prov:startTime": "2012-02-16T18:42:32", "prov:endTime": "2012-02-16T18:42:38", "prov:type": {"$": "collabmap:RouteVerification", "type": "prov:QUALIFIED_NAME"}}, "RouteVerification18356": {"prov:startTime": "2012-02-17T15:18:06", "prov:endTime": "2012-02-17T15:18:14", "prov:type": {"$": "collabmap:RouteVerification", "type": "prov:QUALIFIED_NAME"}}, "RouteVerification18927": {"prov:startTime": "2012-02-17T21:41:45", "prov:endTime": "2012-02-17T21:41:52", "prov:type": {"$": "collabmap:RouteVerification", "type": "prov:QUALIFIED_NAME"}}, "RouteVerification19671": {"prov:startTime": "2012-02-18T15:43:06", "prov:endTime": "2012-02-18T15:43:31", "prov:type": {"$": "collabmap:RouteVerification", "type": "prov:QUALIFIED_NAME"}}, "RouteVerification20021": {"prov:startTime": "2012-02-18T21:14:49", "prov:endTime": "2012-02-18T21:15:08", "prov:type": {"$": "collabmap:RouteVerification", "type": "prov:QUALIFIED_NAME"}}}, "entity": {"DownVote24126.0": {"prov:type": {"$": "collabmap:Vote", "type": "prov:QUALIFIED_NAME"}, "prov:value": {"$": -1, "type": "xsd:int"}}, "DownVote25744.0": {"prov:type": {"$": "collabmap:Vote", "type": "prov:QUALIFIED_NAME"}, "prov:value": {"$": -1, "type": "xsd:int"}}, "Route24127.0": {"prov:type": {"$": "collabmap:Route", "type": "prov:QUALIFIED_NAME"}}, "Route25745.0": {"prov:type": {"$": "collabmap:Route", "type": "prov:QUALIFIED_NAME"}}, "RouteSet1647.1": {"prov:type": {"$": "collabmap:RouteSet", "type": "prov:QUALIFIED_NAME"}}, "RouteSet1647.2": {"prov:type": {"$": "collabmap:RouteSet", "type": "prov:QUALIFIED_NAME"}}, "RouteSet1647.3": {"prov:type": {"$": "collabmap:RouteSet", "type": "prov:QUALIFIED_NAME"}}, "UpVote19855.0": {"prov:type": {"$": "collabmap:Vote", "type": "prov:QUALIFIED_NAME"}, "prov:value": {"$": 1, "type": "xsd:int"}}, "UpVote19856.0": {"prov:type": {"$": "collabmap:Vote", "type": "prov:QUALIFIED_NAME"}, "prov:value": {"$": 1, "type": "xsd:int"}}, "UpVote24125.0": {"prov:type": {"$": "collabmap:Vote", "type": "prov:QUALIFIED_NAME"}, "prov:value": {"$": 1, "type": "xsd:int"}}, "UpVote24129.0": {"prov:type": {"$": "collabmap:Vote", "type": "prov:QUALIFIED_NAME"}, "prov:value": {"$": 1, "type": "xsd:int"}}, "UpVote25743.0": {"prov:type": {"$": "collabmap:Vote", "type": "prov:QUALIFIED_NAME"}, "prov:value": {"$": 1, "type": "xsd:int"}}, "UpVote25747.0": {"prov:type": {"$": "collabmap:Vote", "type": "prov:QUALIFIED_NAME"}, "prov:value": {"$": 1, "type": "xsd:int"}}, "UpVote26728.0": {"prov:type": {"$": "collabmap:Vote", "type": "prov:QUALIFIED_NAME"}, "prov:value": {"$": 1, "type": "xsd:int"}}, "UpVote26729.0": {"prov:type": {"$": "collabmap:Vote", "type": "prov:QUALIFIED_NAME"}, "prov:value": {"$": 1, "type": "xsd:int"}}, "UpVote28934.0": {"prov:type": {"$": "collabmap:Vote", "type": "prov:QUALIFIED_NAME"}, "prov:value": {"$": 1, "type": "xsd:int"}}, "UpVote28935.0": {"prov:type": {"$": "collabmap:Vote", "type": "prov:QUALIFIED_NAME"}, "prov:value": {"$": 1, "type": "xsd:int"}}, "UpVote28936.0": {"prov:type": {"$": "collabmap:Vote", "type": "prov:QUALIFIED_NAME"}, "prov:value": {"$": 1, "type": "xsd:int"}}, "UpVote29732.0": {"prov:type": {"$": "collabmap:Vote", "type": "prov:QUALIFIED_NAME"}, "prov:value": {"$": 1, "type": "xsd:int"}}, "UpVote29733.0": {"prov:type": {"$": "collabmap:Vote", "type": "prov:QUALIFIED_NAME"}, "prov:value": {"$": 1, "type": "xsd:int"}}, "UpVote29734.0": {"prov:type": {"$": "collabmap:Vote", "type": "prov:QUALIFIED_NAME"}, "prov:value": {"$": 1, "type": "xsd:int"}}, "UpVote31275.0": {"prov:type": {"$": "collabmap:Vote", "type": "prov:QUALIFIED_NAME"}, "prov:value": {"$": 1, "type": "xsd:int"}}, "UpVote31276.0": {"prov:type": {"$": "collabmap:Vote", "type": "prov:QUALIFIED_NAME"}, "prov:value": {"$": 1, "type": "xsd:int"}}, "UpVote31277.0": {"prov:type": {"$": "collabmap:Vote", "type": "prov:QUALIFIED_NAME"}, "prov:value": {"$": 1, "type": "xsd:int"}}, "UpVote31895.0": {"prov:type": {"$": "collabmap:Vote", "type": "prov:QUALIFIED_NAME"}, "prov:value": {"$": 1, "type": "xsd:int"}}, "UpVote31896.0": {"prov:type": {"$": "collabmap:Vote", "type": "prov:QUALIFIED_NAME"}, "prov:value": {"$": 1, "type": "xsd:int"}}, "UpVote31897.0": {"prov:type": {"$": "collabmap:Vote", "type": "prov:QUALIFIED_NAME"}, "prov:value": {"$": 1, "type": "xsd:int"}}}, "used": {"_:id1": {"prov:activity": "CompletionVerification12501", "prov:entity": "RouteSet1647.1", "prov:time": "2012-02-14T03:55:48"}, "_:id2": {"prov:activity": "CompletionVerification15281", "prov:entity": "RouteSet1647.1", "prov:time": "2012-02-15T23:09:15"}, "_:id3": {"prov:activity": "CompletionVerification16267", "prov:entity": "RouteSet1647.1", "prov:time": "2012-02-16T15:42:12"}, "_:id4": {"prov:activity": "CompletionVerification16921", "prov:entity": "RouteSet1647.1", "prov:time": "2012-02-16T18:42:38"}, "_:id5": {"prov:activity": "CompletionVerification18357", "prov:entity": "RouteSet1647.2", "prov:time": "2012-02-17T15:18:14"}, "_:id6": {"prov:activity": "CompletionVerification18928", "prov:entity": "RouteSet1647.3", "prov:time": "2012-02-17T21:41:52"}, "_:id7": {"prov:activity": "CompletionVerification19672", "prov:entity": "RouteSet1647.2", "prov:time": "2012-02-18T15:43:31"}, "_:id8": {"prov:activity": "CompletionVerification20022", "prov:entity": "RouteSet1647.2", "prov:time": "2012-02-18T21:15:08"}, "_:id9": {"prov:activity": "RouteIdentification15282", "prov:entity": "RouteSet1647.1", "prov:time": "2012-02-15T23:09:16"}, "_:id10": {"prov:activity": "RouteIdentification16268", "prov:entity": "RouteSet1647.1", "prov:time": "2012-02-16T15:42:13"}, "_:id11": {"prov:activity": "RouteVerification12500", "prov:entity": "RouteSet1647.1", "prov:time": "2012-02-14T03:55:46"}, "_:id12": {"prov:activity": "RouteVerification15280", "prov:entity": "RouteSet1647.1", "prov:time": "2012-02-15T23:09:10"}, "_:id13": {"prov:activity": "RouteVerification16266", "prov:entity": "RouteSet1647.1", "prov:time": "2012-02-16T15:41:40"}, "_:id14": {"prov:activity": "RouteVerification16920", "prov:entity": "RouteSet1647.1", "prov:time": "2012-02-16T18:42:32"}, "_:id15": {"prov:activity": "RouteVerification18356", "prov:entity": "RouteSet1647.2", "prov:time": "2012-02-17T15:18:06"}, "_:id16": {"prov:activity": "RouteVerification18356", "prov:entity": "Route24127.0", "prov:time": "2012-02-17T15:18:06"}, "_:id17": {"prov:activity": "RouteVerification18927", "prov:entity": "RouteSet1647.3", "prov:time": "2012-02-17T21:41:45"}, "_:id18": {"prov:activity": "RouteVerification18927", "prov:entity": "Route25745.0", "prov:time": "2012-02-17T21:41:45"}, "_:id19": {"prov:activity": "RouteVerification19671", "prov:entity": "RouteSet1647.2", "prov:time": "2012-02-18T15:43:06"}, "_:id20": {"prov:activity": "RouteVerification19671", "prov:entity": "Route24127.0", "prov:time": "2012-02-18T15:43:06"}, "_:id21": {"prov:activity": "RouteVerification20021", "prov:entity": "RouteSet1647.2", "prov:time": "2012-02-18T21:14:49"}, "_:id22": {"prov:activity": "RouteVerification20021", "prov:entity": "Route24127.0", "prov:time": "2012-02-18T21:14:49"}}, "wasDerivedFrom": {"_:id23": {"prov:generatedEntity": "DownVote24126.0", "prov:usedEntity": "RouteSet1647.1", "prov:type": {"$": "collabmap:votedOn", "type": "prov:QUALIFIED_NAME"}}, "_:id25": {"prov:generatedEntity": "DownVote25744.0", "prov:usedEntity": "RouteSet1647.1", "prov:type": {"$": "collabmap:votedOn", "type": "prov:QUALIFIED_NAME"}}, "_:id27": {"prov:generatedEntity": "Route24127.0", "prov:usedEntity": "RouteSet1647.1"}, "_:id29": {"prov:generatedEntity": "Route25745.0", "prov:usedEntity": "RouteSet1647.1"}, "_:id31": {"prov:generatedEntity": "RouteSet1647.2", "prov:usedEntity": "RouteSet1647.1", "prov:type": {"$": "prov:Revision", "type": "prov:QUALIFIED_NAME"}}, "_:id32": {"prov:generatedEntity": "RouteSet1647.2", "prov:usedEntity": "Route24127.0", "prov:type": {"$": "collabmap:includes", "type": "prov:QUALIFIED_NAME"}}, "_:id34": {"prov:generatedEntity": "RouteSet1647.3", "prov:usedEntity": "RouteSet1647.1", "prov:type": {"$": "prov:Revision", "type": "prov:QUALIFIED_NAME"}}, "_:id35": {"prov:generatedEntity": "RouteSet1647.3", "prov:usedEntity": "Route25745.0", "prov:type": {"$": "collabmap:includes", "type": "prov:QUALIFIED_NAME"}}, "_:id37": {"prov:generatedEntity": "UpVote19855.0", "prov:usedEntity": "RouteSet1647.1"}, "_:id39": {"prov:generatedEntity": "UpVote19856.0", "prov:usedEntity": "RouteSet1647.1", "prov:type": {"$": "collabmap:votedOn", "type": "prov:QUALIFIED_NAME"}}, "_:id41": {"prov:generatedEntity": "UpVote24125.0", "prov:usedEntity": "RouteSet1647.1"}, "_:id43": {"prov:generatedEntity": "UpVote24129.0", "prov:usedEntity": "Route24127.0", "prov:type": {"$": "collabmap:votedOn", "type": "prov:QUALIFIED_NAME"}}, "_:id44": {"prov:generatedEntity": "UpVote24129.0", "prov:usedEntity": "RouteSet1647.1"}, "_:id46": {"prov:generatedEntity": "UpVote25743.0", "prov:usedEntity": "RouteSet1647.1"}, "_:id48": {"prov:generatedEntity": "UpVote25747.0", "prov:usedEntity": "Route25745.0", "prov:type": {"$": "collabmap:votedOn", "type": "prov:QUALIFIED_NAME"}}, "_:id49": {"prov:generatedEntity": "UpVote25747.0", "prov:usedEntity": "RouteSet1647.1"}, "_:id51": {"prov:generatedEntity": "UpVote26728.0", "prov:usedEntity": "RouteSet1647.1"}, "_:id53": {"prov:generatedEntity": "UpVote26729.0", "prov:usedEntity": "RouteSet1647.1", "prov:type": {"$": "collabmap:votedOn", "type": "prov:QUALIFIED_NAME"}}, "_:id55": {"prov:generatedEntity": "UpVote28934.0", "prov:usedEntity": "RouteSet1647.2"}, "_:id57": {"prov:generatedEntity": "UpVote28935.0", "prov:usedEntity": "Route24127.0", "prov:type": {"$": "collabmap:votedOn", "type": "prov:QUALIFIED_NAME"}}, "_:id58": {"prov:generatedEntity": "UpVote28935.0", "prov:usedEntity": "RouteSet1647.2"}, "_:id60": {"prov:generatedEntity": "UpVote28936.0", "prov:usedEntity": "RouteSet1647.2", "prov:type": {"$": "collabmap:votedOn", "type": "prov:QUALIFIED_NAME"}}, "_:id62": {"prov:generatedEntity": "UpVote29732.0", "prov:usedEntity": "RouteSet1647.3"}, "_:id64": {"prov:generatedEntity": "UpVote29733.0", "prov:usedEntity": "Route25745.0", "prov:type": {"$": "collabmap:votedOn", "type": "prov:QUALIFIED_NAME"}}, "_:id65": {"prov:generatedEntity": "UpVote29733.0", "prov:usedEntity": "RouteSet1647.3"}, "_:id67": {"prov:generatedEntity": "UpVote29734.0", "prov:usedEntity": "RouteSet1647.3", "prov:type": {"$": "collabmap:votedOn", "type": "prov:QUALIFIED_NAME"}}, "_:id69": {"prov:generatedEntity": "UpVote31275.0", "prov:usedEntity": "RouteSet1647.2"}, "_:id71": {"prov:generatedEntity": "UpVote31276.0", "prov:usedEntity": "Route24127.0", "prov:type": {"$": "collabmap:votedOn", "type": "prov:QUALIFIED_NAME"}}, "_:id72": {"prov:generatedEntity": "UpVote31276.0", "prov:usedEntity": "RouteSet1647.2"}, "_:id74": {"prov:generatedEntity": "UpVote31277.0", "prov:usedEntity": "RouteSet1647.2", "prov:type": {"$": "collabmap:votedOn", "type": "prov:QUALIFIED_NAME"}}, "_:id76": {"prov:generatedEntity": "UpVote31895.0", "prov:usedEntity": "RouteSet1647.2"}, "_:id78": {"prov:generatedEntity": "UpVote31896.0", "prov:usedEntity": "Route24127.0", "prov:type": {"$": "collabmap:votedOn", "type": "prov:QUALIFIED_NAME"}}, "_:id79": {"prov:generatedEntity": "UpVote31896.0", "prov:usedEntity": "RouteSet1647.2"}, "_:id81": {"prov:generatedEntity": "UpVote31897.0", "prov:usedEntity": "RouteSet1647.2", "prov:type": {"$": "collabmap:votedOn", "type": "prov:QUALIFIED_NAME"}}}, "wasGeneratedBy": {"_:id24": {"prov:entity": "DownVote24126.0", "prov:activity": "CompletionVerification15281", "prov:time": "2012-02-15T23:09:16"}, "_:id26": {"prov:entity": "DownVote25744.0", "prov:activity": "CompletionVerification16267", "prov:time": "2012-02-16T15:42:13"}, "_:id28": {"prov:entity": "Route24127.0", "prov:activity": "RouteIdentification15282", "prov:time": "2012-02-15T23:09:22"}, "_:id30": {"prov:entity": "Route25745.0", "prov:activity": "RouteIdentification16268", "prov:time": "2012-02-16T15:42:22"}, "_:id33": {"prov:entity": "RouteSet1647.2", "prov:activity": "RouteIdentification15282", "prov:time": "2012-02-15T23:09:22"}, "_:id36": {"prov:entity": "RouteSet1647.3", "prov:activity": "RouteIdentification16268", "prov:time": "2012-02-16T15:42:22"}, "_:id38": {"prov:entity": "UpVote19855.0", "prov:activity": "RouteVerification12500", "prov:time": "2012-02-14T03:55:48"}, "_:id40": {"prov:entity": "UpVote19856.0", "prov:activity": "CompletionVerification12501", "prov:time": "2012-02-14T03:55:50"}, "_:id42": {"prov:entity": "UpVote24125.0", "prov:activity": "RouteVerification15280", "prov:time": "2012-02-15T23:09:15"}, "_:id45": {"prov:entity": "UpVote24129.0", "prov:activity": "RouteIdentification15282", "prov:time": "2012-02-15T23:09:22"}, "_:id47": {"prov:entity": "UpVote25743.0", "prov:activity": "RouteVerification16266", "prov:time": "2012-02-16T15:42:12"}, "_:id50": {"prov:entity": "UpVote25747.0", "prov:activity": "RouteIdentification16268", "prov:time": "2012-02-16T15:42:22"}, "_:id52": {"prov:entity": "UpVote26728.0", "prov:activity": "RouteVerification16920", "prov:time": "2012-02-16T18:42:38"}, "_:id54": {"prov:entity": "UpVote26729.0", "prov:activity": "CompletionVerification16921", "prov:time": "2012-02-16T18:42:39"}, "_:id56": {"prov:entity": "UpVote28934.0", "prov:activity": "RouteVerification18356", "prov:time": "2012-02-17T15:18:14"}, "_:id59": {"prov:entity": "UpVote28935.0", "prov:activity": "RouteVerification18356", "prov:time": "2012-02-17T15:18:14"}, "_:id61": {"prov:entity": "UpVote28936.0", "prov:activity": "CompletionVerification18357", "prov:time": "2012-02-17T15:18:15"}, "_:id63": {"prov:entity": "UpVote29732.0", "prov:activity": "RouteVerification18927", "prov:time": "2012-02-17T21:41:52"}, "_:id66": {"prov:entity": "UpVote29733.0", "prov:activity": "RouteVerification18927", "prov:time": "2012-02-17T21:41:52"}, "_:id68": {"prov:entity": "UpVote29734.0", "prov:activity": "CompletionVerification18928", "prov:time": "2012-02-17T21:42:43"}, "_:id70": {"prov:entity": "UpVote31275.0", "prov:activity": "RouteVerification19671", "prov:time": "2012-02-18T15:43:31"}, "_:id73": {"prov:entity": "UpVote31276.0", "prov:activity": "RouteVerification19671", "prov:time": "2012-02-18T15:43:31"}, "_:id75": {"prov:entity": "UpVote31277.0", "prov:activity": "CompletionVerification19672", "prov:time": "2012-02-18T15:43:32"}, "_:id77": {"prov:entity": "UpVote31895.0", "prov:activity": "RouteVerification20021", "prov:time": "2012-02-18T21:15:08"}, "_:id80": {"prov:entity": "UpVote31896.0", "prov:activity": "RouteVerification20021", "prov:time": "2012-02-18T21:15:08"}, "_:id82": {"prov:entity": "UpVote31897.0", "prov:activity": "CompletionVerification20022", "prov:time": "2012-02-18T21:15:09"}}}