{"prefix": {"collabmap": "http://www.orchid.ac.uk/ontologies/collabmap.owl#", "default": "http://www.collabmap.org/data/local/20140716/"}, "entity": {"UpVote32180.0": {"prov:type": {"$": "collabmap:Vote", "type": "prov:QUALIFIED_NAME"}, "prov:value": {"$": 1, "type": "xsd:int"}}, "UpVote28973.0": {"prov:type": {"$": "collabmap:Vote", "type": "prov:QUALIFIED_NAME"}, "prov:value": {"$": 1, "type": "xsd:int"}}, "UpVote32181.0": {"prov:type": {"$": "collabmap:Vote", "type": "prov:QUALIFIED_NAME"}, "prov:value": {"$": 1, "type": "xsd:int"}}, "UpVote32617.0": {"prov:type": {"$": "collabmap:Vote", "type": "prov:QUALIFIED_NAME"}, "prov:value": {"$": 1, "type": "xsd:int"}}, "UpVote28972.0": {"prov:type": {"$": "collabmap:Vote", "type": "prov:QUALIFIED_NAME"}, "prov:value": {"$": 1, "type": "xsd:int"}}, "UpVote32619.0": {"prov:type": {"$": "collabmap:Vote", "type": "prov:QUALIFIED_NAME"}, "prov:value": {"$": 1, "type": "xsd:int"}}, "UpVote28971.0": {"prov:type": {"$": "collabmap:Vote", "type": "prov:QUALIFIED_NAME"}, "prov:value": {"$": 1, "type": "xsd:int"}}, "UpVote32182.0": {"prov:type": {"$": "collabmap:Vote", "type": "prov:QUALIFIED_NAME"}, "prov:value": {"$": 1, "type": "xsd:int"}}, "RouteSet2699.2": {"prov:type": {"$": "collabmap:RouteSet", "type": "prov:QUALIFIED_NAME"}}, "UpVote32618.0": {"prov:type": {"$": "collabmap:Vote", "type": "prov:QUALIFIED_NAME"}, "prov:value": {"$": 1, "type": "xsd:int"}}}, "activity": {"CompletionVerification20219": {"prov:startTime": "2012-02-18T23:04:49", "prov:endTime": "2012-02-18T23:04:50", "prov:type": {"$": "collabmap:CompletionVerification", "type": "prov:QUALIFIED_NAME"}}, "RouteVerification20545": {"prov:startTime": "2012-02-19T01:22:36", "prov:endTime": "2012-02-19T01:22:40", "prov:type": {"$": "collabmap:RouteVerification", "type": "prov:QUALIFIED_NAME"}}, "CompletionVerification20546": {"prov:startTime": "2012-02-19T01:22:40", "prov:endTime": "2012-02-19T01:22:41", "prov:type": {"$": "collabmap:CompletionVerification", "type": "prov:QUALIFIED_NAME"}}, "RouteVerification20218": {"prov:startTime": "2012-02-18T23:04:44", "prov:endTime": "2012-02-18T23:04:49", "prov:type": {"$": "collabmap:RouteVerification", "type": "prov:QUALIFIED_NAME"}}, "RouteVerification18377": {"prov:startTime": "2012-02-17T15:29:33", "prov:endTime": "2012-02-17T15:29:39", "prov:type": {"$": "collabmap:RouteVerification", "type": "prov:QUALIFIED_NAME"}}, "CompletionVerification18378": {"prov:startTime": "2012-02-17T15:29:39", "prov:endTime": "2012-02-17T15:29:40", "prov:type": {"$": "collabmap:CompletionVerification", "type": "prov:QUALIFIED_NAME"}}}, "wasDerivedFrom": {"_:id1": {"prov:generatedEntity": "UpVote32180.0", "prov:usedEntity": "RouteSet2699.2"}, "_:id3": {"prov:generatedEntity": "UpVote28973.0", "prov:usedEntity": "RouteSet2699.2", "prov:type": {"$": "collabmap:votedOn", "type": "prov:QUALIFIED_NAME"}}, "_:id6": {"prov:generatedEntity": "UpVote32181.0", "prov:usedEntity": "RouteSet2699.2"}, "_:id9": {"prov:generatedEntity": "UpVote32617.0", "prov:usedEntity": "RouteSet2699.2"}, "_:id11": {"prov:generatedEntity": "UpVote28972.0", "prov:usedEntity": "RouteSet2699.2"}, "_:id14": {"prov:generatedEntity": "UpVote32619.0", "prov:usedEntity": "RouteSet2699.2", "prov:type": {"$": "collabmap:votedOn", "type": "prov:QUALIFIED_NAME"}}, "_:id16": {"prov:generatedEntity": "UpVote28971.0", "prov:usedEntity": "RouteSet2699.2"}, "_:id18": {"prov:generatedEntity": "UpVote32182.0", "prov:usedEntity": "RouteSet2699.2", "prov:type": {"$": "collabmap:votedOn", "type": "prov:QUALIFIED_NAME"}}, "_:id22": {"prov:generatedEntity": "UpVote32618.0", "prov:usedEntity": "RouteSet2699.2"}}, "wasGeneratedBy": {"_:id2": {"prov:entity": "UpVote32180.0", "prov:activity": "RouteVerification20218", "prov:time": "2012-02-18T23:04:49"}, "_:id4": {"prov:entity": "UpVote28973.0", "prov:activity": "CompletionVerification18378", "prov:time": "2012-02-17T15:29:40"}, "_:id7": {"prov:entity": "UpVote32181.0", "prov:activity": "RouteVerification20218", "prov:time": "2012-02-18T23:04:49"}, "_:id10": {"prov:entity": "UpVote32617.0", "prov:activity": "RouteVerification20545", "prov:time": "2012-02-19T01:22:40"}, "_:id12": {"prov:entity": "UpVote28972.0", "prov:activity": "RouteVerification18377", "prov:time": "2012-02-17T15:29:39"}, "_:id15": {"prov:entity": "UpVote32619.0", "prov:activity": "CompletionVerification20546", "prov:time": "2012-02-19T01:22:41"}, "_:id17": {"prov:entity": "UpVote28971.0", "prov:activity": "RouteVerification18377", "prov:time": "2012-02-17T15:29:39"}, "_:id19": {"prov:entity": "UpVote32182.0", "prov:activity": "CompletionVerification20219", "prov:time": "2012-02-18T23:04:50"}, "_:id23": {"prov:entity": "UpVote32618.0", "prov:activity": "RouteVerification20545", "prov:time": "2012-02-19T01:22:40"}}, "used": {"_:id5": {"prov:activity": "CompletionVerification20219", "prov:entity": "RouteSet2699.2", "prov:time": "2012-02-18T23:04:49"}, "_:id8": {"prov:activity": "RouteVerification20545", "prov:entity": "RouteSet2699.2", "prov:time": "2012-02-19T01:22:36"}, "_:id13": {"prov:activity": "CompletionVerification20546", "prov:entity": "RouteSet2699.2", "prov:time": "2012-02-19T01:22:40"}, "_:id20": {"prov:activity": "RouteVerification20218", "prov:entity": "RouteSet2699.2", "prov:time": "2012-02-18T23:04:44"}, "_:id21": {"prov:activity": "RouteVerification18377", "prov:entity": "RouteSet2699.2", "prov:time": "2012-02-17T15:29:33"}, "_:id24": {"prov:activity": "CompletionVerification18378", "prov:entity": "RouteSet2699.2", "prov:time": "2012-02-17T15:29:39"}}}