{"prefix": {"collabmap": "http://www.orchid.ac.uk/ontologies/collabmap.owl#", "default": "http://www.collabmap.org/data/local/20140716/"}, "entity": {"UpVote46674.0": {"prov:type": {"$": "collabmap:Vote", "type": "prov:QUALIFIED_NAME"}, "prov:value": {"$": 1, "type": "xsd:int"}}, "UpVote42926.0": {"prov:type": {"$": "collabmap:Vote", "type": "prov:QUALIFIED_NAME"}, "prov:value": {"$": 1, "type": "xsd:int"}}, "UpVote42998.0": {"prov:type": {"$": "collabmap:Vote", "type": "prov:QUALIFIED_NAME"}, "prov:value": {"$": 1, "type": "xsd:int"}}, "UpVote42997.0": {"prov:type": {"$": "collabmap:Vote", "type": "prov:QUALIFIED_NAME"}, "prov:value": {"$": 1, "type": "xsd:int"}}, "UpVote42927.0": {"prov:type": {"$": "collabmap:Vote", "type": "prov:QUALIFIED_NAME"}, "prov:value": {"$": 1, "type": "xsd:int"}}, "UpVote46675.0": {"prov:type": {"$": "collabmap:Vote", "type": "prov:QUALIFIED_NAME"}, "prov:value": {"$": 1, "type": "xsd:int"}}, "RouteSet4812.1": {"prov:type": {"$": "collabmap:RouteSet", "type": "prov:QUALIFIED_NAME"}}}, "activity": {"RouteVerification27407": {"prov:startTime": "2012-02-20T21:05:28", "prov:endTime": "2012-02-20T21:05:51", "prov:type": {"$": "collabmap:RouteVerification", "type": "prov:QUALIFIED_NAME"}}, "RouteVerification27459": {"prov:startTime": "2012-02-20T21:12:36", "prov:endTime": "2012-02-20T21:12:49", "prov:type": {"$": "collabmap:RouteVerification", "type": "prov:QUALIFIED_NAME"}}, "CompletionVerification27460": {"prov:startTime": "2012-02-20T21:12:49", "prov:endTime": "2012-02-20T21:12:50", "prov:type": {"$": "collabmap:CompletionVerification", "type": "prov:QUALIFIED_NAME"}}, "CompletionVerification27408": {"prov:startTime": "2012-02-20T21:05:51", "prov:endTime": "2012-02-20T21:05:53", "prov:type": {"$": "collabmap:CompletionVerification", "type": "prov:QUALIFIED_NAME"}}, "CompletionVerification30050": {"prov:startTime": "2012-02-21T20:17:38", "prov:endTime": "2012-02-21T20:17:39", "prov:type": {"$": "collabmap:CompletionVerification", "type": "prov:QUALIFIED_NAME"}}, "RouteVerification30049": {"prov:startTime": "2012-02-21T20:17:13", "prov:endTime": "2012-02-21T20:17:38", "prov:type": {"$": "collabmap:RouteVerification", "type": "prov:QUALIFIED_NAME"}}}, "wasDerivedFrom": {"_:id1": {"prov:generatedEntity": "UpVote46674.0", "prov:usedEntity": "RouteSet4812.1"}, "_:id6": {"prov:generatedEntity": "UpVote42926.0", "prov:usedEntity": "RouteSet4812.1"}, "_:id8": {"prov:generatedEntity": "UpVote42998.0", "prov:usedEntity": "RouteSet4812.1", "prov:type": {"$": "collabmap:votedOn", "type": "prov:QUALIFIED_NAME"}}, "_:id10": {"prov:generatedEntity": "UpVote42997.0", "prov:usedEntity": "RouteSet4812.1"}, "_:id12": {"prov:generatedEntity": "UpVote42927.0", "prov:usedEntity": "RouteSet4812.1", "prov:type": {"$": "collabmap:votedOn", "type": "prov:QUALIFIED_NAME"}}, "_:id16": {"prov:generatedEntity": "UpVote46675.0", "prov:usedEntity": "RouteSet4812.1", "prov:type": {"$": "collabmap:votedOn", "type": "prov:QUALIFIED_NAME"}}}, "wasGeneratedBy": {"_:id2": {"prov:entity": "UpVote46674.0", "prov:activity": "RouteVerification30049", "prov:time": "2012-02-21T20:17:38"}, "_:id7": {"prov:entity": "UpVote42926.0", "prov:activity": "RouteVerification27407", "prov:time": "2012-02-20T21:05:51"}, "_:id9": {"prov:entity": "UpVote42998.0", "prov:activity": "CompletionVerification27460", "prov:time": "2012-02-20T21:12:50"}, "_:id11": {"prov:entity": "UpVote42997.0", "prov:activity": "RouteVerification27459", "prov:time": "2012-02-20T21:12:49"}, "_:id13": {"prov:entity": "UpVote42927.0", "prov:activity": "CompletionVerification27408", "prov:time": "2012-02-20T21:05:53"}, "_:id17": {"prov:entity": "UpVote46675.0", "prov:activity": "CompletionVerification30050", "prov:time": "2012-02-21T20:17:39"}}, "used": {"_:id3": {"prov:activity": "RouteVerification27407", "prov:entity": "RouteSet4812.1", "prov:time": "2012-02-20T21:05:28"}, "_:id4": {"prov:activity": "RouteVerification27459", "prov:entity": "RouteSet4812.1", "prov:time": "2012-02-20T21:12:36"}, "_:id5": {"prov:activity": "CompletionVerification27460", "prov:entity": "RouteSet4812.1", "prov:time": "2012-02-20T21:12:49"}, "_:id14": {"prov:activity": "CompletionVerification27408", "prov:entity": "RouteSet4812.1", "prov:time": "2012-02-20T21:05:51"}, "_:id15": {"prov:activity": "CompletionVerification30050", "prov:entity": "RouteSet4812.1", "prov:time": "2012-02-21T20:17:38"}, "_:id18": {"prov:activity": "RouteVerification30049", "prov:entity": "RouteSet4812.1", "prov:time": "2012-02-21T20:17:13"}}}