{"prefix": {"collabmap": "http://www.orchid.ac.uk/ontologies/collabmap.owl#", "default": "http://www.collabmap.org/data/local/20140716/"}, "activity": {"RouteVerification37451": {"prov:startTime": "2012-02-24T10:15:30", "prov:endTime": "2012-02-24T10:15:34", "prov:type": {"$": "collabmap:RouteVerification", "type": "prov:QUALIFIED_NAME"}}, "CompletionVerification37452": {"prov:startTime": "2012-02-24T10:15:34", "prov:endTime": "2012-02-24T10:15:34", "prov:type": {"$": "collabmap:CompletionVerification", "type": "prov:QUALIFIED_NAME"}}}, "entity": {"UpVote57709.0": {"prov:type": {"$": "collabmap:Vote", "type": "prov:QUALIFIED_NAME"}, "prov:value": {"$": 1, "type": "xsd:int"}}, "UpVote57705.0": {"prov:type": {"$": "collabmap:Vote", "type": "prov:QUALIFIED_NAME"}, "prov:value": {"$": 1, "type": "xsd:int"}}, "Route57703.0": {"prov:type": {"$": "collabmap:Route", "type": "prov:QUALIFIED_NAME"}}, "RouteSet7191.1": {"prov:type": {"$": "collabmap:RouteSet", "type": "prov:QUALIFIED_NAME"}}, "UpVote57710.0": {"prov:type": {"$": "collabmap:Vote", "type": "prov:QUALIFIED_NAME"}, "prov:value": {"$": 1, "type": "xsd:int"}}}, "used": {"_:id1": {"prov:activity": "RouteVerification37451", "prov:entity": "RouteSet7191.1", "prov:time": "2012-02-24T10:15:30"}, "_:id2": {"prov:activity": "RouteVerification37451", "prov:entity": "Route57703.0", "prov:time": "2012-02-24T10:15:30"}, "_:id8": {"prov:activity": "CompletionVerification37452", "prov:entity": "RouteSet7191.1", "prov:time": "2012-02-24T10:15:34"}}, "wasDerivedFrom": {"_:id3": {"prov:generatedEntity": "UpVote57709.0", "prov:usedEntity": "Route57703.0", "prov:type": {"$": "collabmap:votedOn", "type": "prov:QUALIFIED_NAME"}}, "_:id4": {"prov:generatedEntity": "UpVote57709.0", "prov:usedEntity": "RouteSet7191.1"}, "_:id6": {"prov:generatedEntity": "UpVote57705.0", "prov:usedEntity": "Route57703.0", "prov:type": {"$": "collabmap:votedOn", "type": "prov:QUALIFIED_NAME"}}, "_:id7": {"prov:generatedEntity": "RouteSet7191.1", "prov:usedEntity": "Route57703.0", "prov:type": {"$": "collabmap:includes", "type": "prov:QUALIFIED_NAME"}}, "_:id9": {"prov:generatedEntity": "UpVote57710.0", "prov:usedEntity": "RouteSet7191.1", "prov:type": {"$": "collabmap:votedOn", "type": "prov:QUALIFIED_NAME"}}}, "wasGeneratedBy": {"_:id5": {"prov:entity": "UpVote57709.0", "prov:activity": "RouteVerification37451", "prov:time": "2012-02-24T10:15:34"}, "_:id10": {"prov:entity": "UpVote57710.0", "prov:activity": "CompletionVerification37452", "prov:time": "2012-02-24T10:15:34"}}}