{"prefix": {"collabmap": "http://www.orchid.ac.uk/ontologies/collabmap.owl#", "default": "http://www.collabmap.org/data/local/20140716/"}, "activity": {"BuildingVerification37132": {"prov:startTime": "2012-02-24T00:19:38", "prov:endTime": "2012-02-24T00:19:39", "prov:type": {"$": "collabmap:BuildingVerification", "type": "prov:QUALIFIED_NAME"}}, "BuildingVerification9771": {"prov:startTime": "2012-02-13T18:31:32", "prov:endTime": "2012-02-13T18:31:33", "prov:type": {"$": "collabmap:BuildingVerification", "type": "prov:QUALIFIED_NAME"}}, "CompletionVerification37626": {"prov:startTime": "2012-02-24T10:35:48", "prov:endTime": "2012-02-24T10:35:49", "prov:type": {"$": "collabmap:CompletionVerification", "type": "prov:QUALIFIED_NAME"}}, "RouteIdentification37251": {"prov:startTime": "2012-02-24T09:17:33", "prov:endTime": "2012-02-24T09:17:53", "prov:type": {"$": "collabmap:RouteIdentification", "type": "prov:QUALIFIED_NAME"}}, "RouteVerification37625": {"prov:startTime": "2012-02-24T10:35:47", "prov:endTime": "2012-02-24T10:35:48", "prov:type": {"$": "collabmap:RouteVerification", "type": "prov:QUALIFIED_NAME"}}}, "entity": {"Building7311.0": {"prov:type": {"$": "collabmap:Building", "type": "prov:QUALIFIED_NAME"}}, "Route57435.0": {"prov:type": {"$": "collabmap:Route", "type": "prov:QUALIFIED_NAME"}}, "RouteSet7311.1": {"prov:type": {"$": "collabmap:RouteSet", "type": "prov:QUALIFIED_NAME"}}, "UpVote15951.0": {"prov:type": {"$": "collabmap:Vote", "type": "prov:QUALIFIED_NAME"}, "prov:value": {"$": 1, "type": "xsd:int"}}, "UpVote57241.0": {"prov:type": {"$": "collabmap:Vote", "type": "prov:QUALIFIED_NAME"}, "prov:value": {"$": 1, "type": "xsd:int"}}, "UpVote57437.0": {"prov:type": {"$": "collabmap:Vote", "type": "prov:QUALIFIED_NAME"}, "prov:value": {"$": 1, "type": "xsd:int"}}, "UpVote58007.0": {"prov:type": {"$": "collabmap:Vote", "type": "prov:QUALIFIED_NAME"}, "prov:value": {"$": 1, "type": "xsd:int"}}, "UpVote58008.0": {"prov:type": {"$": "collabmap:Vote", "type": "prov:QUALIFIED_NAME"}, "prov:value": {"$": 1, "type": "xsd:int"}}, "UpVote7312.0": {"prov:type": {"$": "collabmap:Vote", "type": "prov:QUALIFIED_NAME"}, "prov:value": {"$": 1, "type": "xsd:int"}}}, "used": {"_:id1": {"prov:activity": "BuildingVerification37132", "prov:entity": "Building7311.0", "prov:time": "2012-02-24T00:19:38"}, "_:id2": {"prov:activity": "BuildingVerification9771", "prov:entity": "Building7311.0", "prov:time": "2012-02-13T18:31:32"}, "_:id3": {"prov:activity": "CompletionVerification37626", "prov:entity": "RouteSet7311.1", "prov:time": "2012-02-24T10:35:48"}, "_:id4": {"prov:activity": "RouteIdentification37251", "prov:entity": "Building7311.0", "prov:time": "2012-02-24T09:17:33"}, "_:id5": {"prov:activity": "RouteVerification37625", "prov:entity": "RouteSet7311.1", "prov:time": "2012-02-24T10:35:47"}, "_:id6": {"prov:activity": "RouteVerification37625", "prov:entity": "Route57435.0", "prov:time": "2012-02-24T10:35:47"}}, "wasDerivedFrom": {"_:id7": {"prov:generatedEntity": "Route57435.0", "prov:usedEntity": "Building7311.0"}, "_:id9": {"prov:generatedEntity": "RouteSet7311.1", "prov:usedEntity": "Building7311.0", "prov:type": {"$": "prov:Revision", "type": "prov:QUALIFIED_NAME"}}, "_:id10": {"prov:generatedEntity": "RouteSet7311.1", "prov:usedEntity": "Route57435.0", "prov:type": {"$": "collabmap:includes", "type": "prov:QUALIFIED_NAME"}}, "_:id12": {"prov:generatedEntity": "UpVote15951.0", "prov:usedEntity": "Building7311.0", "prov:type": {"$": "collabmap:votedOn", "type": "prov:QUALIFIED_NAME"}}, "_:id14": {"prov:generatedEntity": "UpVote57241.0", "prov:usedEntity": "Building7311.0", "prov:type": {"$": "collabmap:votedOn", "type": "prov:QUALIFIED_NAME"}}, "_:id16": {"prov:generatedEntity": "UpVote57437.0", "prov:usedEntity": "Route57435.0", "prov:type": {"$": "collabmap:votedOn", "type": "prov:QUALIFIED_NAME"}}, "_:id17": {"prov:generatedEntity": "UpVote57437.0", "prov:usedEntity": "Building7311.0"}, "_:id19": {"prov:generatedEntity": "UpVote58007.0", "prov:usedEntity": "Route57435.0", "prov:type": {"$": "collabmap:votedOn", "type": "prov:QUALIFIED_NAME"}}, "_:id20": {"prov:generatedEntity": "UpVote58007.0", "prov:usedEntity": "RouteSet7311.1"}, "_:id22": {"prov:generatedEntity": "UpVote58008.0", "prov:usedEntity": "RouteSet7311.1", "prov:type": {"$": "collabmap:votedOn", "type": "prov:QUALIFIED_NAME"}}, "_:id24": {"prov:generatedEntity": "UpVote7312.0", "prov:usedEntity": "Building7311.0", "prov:type": {"$": "collabmap:votedOn", "type": "prov:QUALIFIED_NAME"}}}, "wasGeneratedBy": {"_:id8": {"prov:entity": "Route57435.0", "prov:activity": "RouteIdentification37251", "prov:time": "2012-02-24T09:17:53"}, "_:id11": {"prov:entity": "RouteSet7311.1", "prov:activity": "RouteIdentification37251", "prov:time": "2012-02-24T09:17:53"}, "_:id13": {"prov:entity": "UpVote15951.0", "prov:activity": "BuildingVerification9771", "prov:time": "2012-02-13T18:31:33"}, "_:id15": {"prov:entity": "UpVote57241.0", "prov:activity": "BuildingVerification37132", "prov:time": "2012-02-24T00:19:39"}, "_:id18": {"prov:entity": "UpVote57437.0", "prov:activity": "RouteIdentification37251", "prov:time": "2012-02-24T09:17:53"}, "_:id21": {"prov:entity": "UpVote58007.0", "prov:activity": "RouteVerification37625", "prov:time": "2012-02-24T10:35:48"}, "_:id23": {"prov:entity": "UpVote58008.0", "prov:activity": "CompletionVerification37626", "prov:time": "2012-02-24T10:35:49"}}}